{
  "bio": "",
  "badges": [{
    "name": "gdg",
    "description": "GDG Presidente Prudente",
    "link": "https://gdgprudente.org"
  }],
  "shortBio": "",
  "photoUrl": "https://firebasestorage.googleapis.com/v0/b/devfest-pr-2018.appspot.com/o/speakers%2Fjoao-cunha.jpg?alt=media&token=e53007d5-9d8e-4b1e-b91f-eb62f7ce0314",
  "name": "João Cunha",
  "companyLogo": "https://firebasestorage.googleapis.com/v0/b/devfest-pr-2018.appspot.com/o/companies%2Fforegon.png?alt=media&token=9bc58600-f6ed-4214-8b3a-4aa4c253da1b",
  "title": "Product Manager",
  "photo": "https://firebasestorage.googleapis.com/v0/b/devfest-pr-2018.appspot.com/o/speakers%2Fjoao-cunha.jpg?alt=media&token=e53007d5-9d8e-4b1e-b91f-eb62f7ce0314",
  "order": 13,
  "featured": false,
  "company": "Foregon",
  "companyLogoUrl": "https://firebasestorage.googleapis.com/v0/b/devfest-pr-2018.appspot.com/o/companies%2Fforegon.png?alt=media&token=9bc58600-f6ed-4214-8b3a-4aa4c253da1b",
  "socials": [{
    "name": "Twitter",
    "icon": "twitter",
    "link": "https://twitter.com/joaocunha"
  }, {
    "name": "LinkedIn",
    "icon": "linkedin",
    "link": "https://www.linkedin.com/in/joaocunhadev"
  }, {
    "name": "GitHub",
    "icon": "github",
    "link": "https://github.com/joaocunha"
  }],
  "country": "Presidente Prudente, São Paulo"
}
